dora_cdk_constructs/__init__.py
dora_cdk_constructs/catalog.py
dora_cdk_constructs/engines.py
dora_cdk_constructs/functions/consumer/handler.py
dora_cdk_constructs/pipeline.py
dora_cdk_constructs/utils.py
dora_cdk_constructs-0.1.0.dist-info/LICENSE
dora_cdk_constructs-0.1.0.dist-info/METADATA
dora_cdk_constructs-0.1.0.dist-info/WHEEL
dora_cdk_constructs-0.1.0.dist-info/RECORD
