Metadata-Version: 2.1
Name: dora-cdk-constructs
Version: 0.1.0
Summary: Use this Dora CDK Construct Library to deploy applications using AWS CDK
License: Apache-2.0
Author: Didone
Author-email: tiago.didone@compass.uol
Requires-Python: >=3.10,<3.13
Classifier: License :: OSI Approved :: Apache Software License
Classifier: Programming Language :: Python :: 3
Classifier: Programming Language :: Python :: 3.10
Classifier: Programming Language :: Python :: 3.11
Classifier: Programming Language :: Python :: 3.12
Requires-Dist: aws-cdk-lib (>=2.177.0,<3.0.0)
Requires-Dist: cdk-ecr-deployment (>=3.1.9,<4.0.0)
Requires-Dist: constructs (>=10.4.2,<11.0.0)
Requires-Dist: dora-aws (>=0.1.0,<0.2.0)
